ailab_api/__init__.py
ailab_api/sendMsg.py
ailab_api-0.7.dist-info/METADATA
ailab_api-0.7.dist-info/WHEEL
ailab_api-0.7.dist-info/top_level.txt
ailab_api-0.7.dist-info/RECORD
