Metadata-Version: 2.1
Name: ailab-api
Version: 0.7
Summary: ailab-daejin-restful-api
Home-page: https://github.com/GoopyAspirin/ailab-api
Author: donggu.kang
Author-email: kang154123@naver.com
License: UNKNOWN
Download-URL: https://github.com/GoopyAspirin/ailab-api/download/ailab-api-0.4.tar.gz
Keywords: api
Platform: UNKNOWN
Classifier: Programming Language :: Python :: 3
Classifier: Programming Language :: Python :: 3.2
Classifier: Programming Language :: Python :: 3.3
Classifier: Programming Language :: Python :: 3.4
Classifier: Programming Language :: Python :: 3.5
Classifier: Programming Language :: Python :: 3.6
Classifier: Programming Language :: Python :: 3.7
Requires-Python: >=3
Requires-Dist: requests
